reportcraft/__init__.py
reportcraft/admin.py
reportcraft/apps.py
reportcraft/countries.py
reportcraft/entries.py
reportcraft/forms.py
reportcraft/functions/__init__.py
reportcraft/functions/postgres.py
reportcraft/migrations/0001_initial.py
reportcraft/migrations/0002_alter_datamodel_name_alter_entry_kind.py
reportcraft/migrations/0003_alter_entry_kind.py
reportcraft/migrations/0004_report_section.py
reportcraft/migrations/0005_datasource_description.py
reportcraft/migrations/0006_alter_datafield_options_alter_datamodel_options_and_more.py
reportcraft/migrations/0007_alter_datasource_filters.py
reportcraft/migrations/0008_alter_report_section.py
reportcraft/migrations/0009_refactor_bar_entries.py
reportcraft/migrations/0010_alter_entry_kind.py
reportcraft/migrations/0011_remove_report_style_report_theme.py
reportcraft/migrations/0012_entry_filters.py
reportcraft/migrations/0013_alter_entry_kind.py
reportcraft/migrations/0014_add_uuid_fields.py
reportcraft/migrations/0015_populate_uuid_fields.py
reportcraft/migrations/0016_remove_uuid_null.py
reportcraft/migrations/__init__.py
reportcraft/models.py
reportcraft/static/reportcraft/logo.svg
reportcraft/static/reportcraft/maps/001.json
reportcraft/static/reportcraft/maps/002.json
reportcraft/static/reportcraft/maps/003.json
reportcraft/static/reportcraft/maps/005.json
reportcraft/static/reportcraft/maps/009.json
reportcraft/static/reportcraft/maps/010.json
reportcraft/static/reportcraft/maps/011.json
reportcraft/static/reportcraft/maps/013.json
reportcraft/static/reportcraft/maps/014.json
reportcraft/static/reportcraft/maps/015.json
reportcraft/static/reportcraft/maps/017.json
reportcraft/static/reportcraft/maps/018.json
reportcraft/static/reportcraft/maps/019.json
reportcraft/static/reportcraft/maps/021.json
reportcraft/static/reportcraft/maps/029.json
reportcraft/static/reportcraft/maps/030.json
reportcraft/static/reportcraft/maps/034.json
reportcraft/static/reportcraft/maps/035.json
django_reportcraft-2026.1.1.dist-info/METADATA
django_reportcraft-2026.1.1.dist-info/WHEEL
django_reportcraft-2026.1.1.dist-info/licenses/LICENSE
django_reportcraft-2026.1.1.dist-info/RECORD
