Metadata-Version: 2.4
Name: django-reportcraft
Version: 2026.1.1
Summary: A Django reusable App for dynamically designing and generating reports for business intelligence.
License-Expression: MIT
License-File: LICENSE
Author: Michel Fodje
Author-email: michel4j@gmail.com
Requires-Python: >=3.12
Classifier: Environment :: Web Environment
Classifier: Framework :: Django
Classifier: Intended Audience :: Developers
Classifier: License :: OSI Approved :: MIT License
Classifier: Operating System :: OS Independent
Classifier: Programming Language :: Python
Classifier: Topic :: Internet :: WWW/HTTP
Classifier: Topic :: Internet :: WWW/HTTP :: Dynamic Content
Classifier: Topic :: Software Development :: Libraries :: Application Frameworks
Classifier: Topic :: Software Development :: Libraries :: Python Modules
Requires-Dist: django (>=5.2.11,<7.0.0)
Requires-Dist: django-crisp-modals (>=2026.1.0)
Requires-Dist: django-itemlist (>=2026.1.7)
Requires-Dist: numpy (>=2.2.4,<3.0.0)
Requires-Dist: pygments (>=2.19.1,<3.0.0)
Requires-Dist: pyparsing (>=3.2.1,<4.0.0)
Project-URL: Documentation, https://michel4j.github.io/django-reportcraft/
Project-URL: Homepage, https://github.com/michel4j/django-reportcraft
Project-URL: Issues, https://github.com/michel4j/django-reportcraft/issues
